{
  "type": "minecraft:stonecutting",
  "ingredient": {
      "item": "minecraft:weathered_copper"
  },
  "result": {
      "id": "minecraft:player_head",
      "count": 1,
      "components": {
          "minecraft:custom_name": "{\"type\":\"translatable\",\"translate\":\"block.minecraft.weathered_copper_block\",\"italic\":false,\"color\":\"yellow\"}",
          "minecraft:profile": {
              "id": [
                2082638824,-722777440,-1513565861,1270388568
              ],
              "properties": [
                  {
                      "name": "textures",
                      "value": "eyJ0ZXh0dXJlcyI6eyJTS0lOIjp7InVybCI6Imh0dHA6Ly90ZXh0dXJlcy5taW5lY3JhZnQubmV0L3RleHR1cmUvZjcwZjUxOWYxNTcxOWU2ZTFhNDIwZGVhODFjZTgxZmRhMGRmNjRhYzhkNGM1NzViNzk1OTllZGRjYjViODA4In19fQ=="
                  }
              ]
          }
      }
  }
}