{
  "type": "minecraft:stonecutting",
  "ingredient": {
      "item": "minecraft:lodestone"
  },
  "result": {
      "id": "minecraft:player_head",
      "count": 1,
      "components": {
          "minecraft:custom_name": "{\"type\":\"translatable\",\"translate\":\"block.minecraft.lodestone\",\"italic\":false,\"color\":\"yellow\"}",
          "minecraft:profile": {
              "id": [
                -1603067143,-88585229,-1777822630,-164656805
              ],
              "properties": [
                  {
                      "name": "textures",
                      "value": "eyJ0ZXh0dXJlcyI6eyJTS0lOIjp7InVybCI6Imh0dHA6Ly90ZXh0dXJlcy5taW5lY3JhZnQubmV0L3RleHR1cmUvZjJjNjE3ODM1OTBiNmU2ODQ3MzAwNWIzMmVjMGEwOGJjM2I5NWQ2NDkwMzZiMzU4YWZlNzdhZDhhZjg4NDgwMCJ9fX0="
                  }
              ]
          }
      }
  }
}