{
  "type": "minecraft:stonecutting",
  "ingredient": {
      "item": "minecraft:netherrack"
  },
  "result": {
      "id": "minecraft:player_head",
      "count": 1,
      "components": {
          "minecraft:custom_name": "{\"type\":\"translatable\",\"translate\":\"block.minecraft.netherrack\",\"italic\":false,\"color\":\"yellow\"}",
          "minecraft:profile": {
              "id": [
                806523663,-1155054857,-2087728779,-579371496
              ],
              "properties": [
                  {
                      "name": "textures",
                      "value": "eyJ0ZXh0dXJlcyI6eyJTS0lOIjp7InVybCI6Imh0dHA6Ly90ZXh0dXJlcy5taW5lY3JhZnQubmV0L3RleHR1cmUvOTljNmEzNzhhNzJkYTE3NTgzMWM5Mzk0ZmE0NWViNzM0M2YzMWQ3ZDA1OGZhNzZhOWE2NDZiZTAwN2I3ODg4ZCJ9fX0="
                  }
              ]
          }
      }
  }
}